awarc/__init__.py
awarc/arc.py
awarc-0.0.4.dist-info/LICENSE
awarc-0.0.4.dist-info/METADATA
awarc-0.0.4.dist-info/WHEEL
awarc-0.0.4.dist-info/top_level.txt
awarc-0.0.4.dist-info/RECORD
